Metadata-Version: 2.1
Name: distributions-proba
Version: 0.1
Summary: Gaussian and binomial distributions
Home-page: UNKNOWN
Author: Gizella Nádor
Author-email: gizella.nador@gmail.com
License: UNKNOWN
Platform: UNKNOWN
